odoo/addons/stock_picking_group_by_max_weight/README.rst
odoo/addons/stock_picking_group_by_max_weight/__init__.py
odoo/addons/stock_picking_group_by_max_weight/__manifest__.py
odoo/addons/stock_picking_group_by_max_weight/hooks.py
odoo/addons/stock_picking_group_by_max_weight/i18n/es.po
odoo/addons/stock_picking_group_by_max_weight/i18n/it.po
odoo/addons/stock_picking_group_by_max_weight/i18n/stock_picking_group_by_max_weight.pot
odoo/addons/stock_picking_group_by_max_weight/models/__init__.py
odoo/addons/stock_picking_group_by_max_weight/models/stock_move.py
odoo/addons/stock_picking_group_by_max_weight/models/stock_picking.py
odoo/addons/stock_picking_group_by_max_weight/models/stock_picking_type.py
odoo/addons/stock_picking_group_by_max_weight/readme/CONFIGURE.rst
odoo/addons/stock_picking_group_by_max_weight/readme/CONTRIBUTORS.rst
odoo/addons/stock_picking_group_by_max_weight/readme/DESCRIPTION.rst
odoo/addons/stock_picking_group_by_max_weight/readme/HISTORY.rst
odoo/addons/stock_picking_group_by_max_weight/readme/newsfragments/.gitignore
odoo/addons/stock_picking_group_by_max_weight/static/description/icon.png
odoo/addons/stock_picking_group_by_max_weight/static/description/index.html
odoo/addons/stock_picking_group_by_max_weight/tests/__init__.py
odoo/addons/stock_picking_group_by_max_weight/tests/test_group_maxweight.py
odoo/addons/stock_picking_group_by_max_weight/views/stock_picking_type.xml
odoo_addon_stock_picking_group_by_max_weight-16.0.1.1.1.dist-info/METADATA
odoo_addon_stock_picking_group_by_max_weight-16.0.1.1.1.dist-info/WHEEL
odoo_addon_stock_picking_group_by_max_weight-16.0.1.1.1.dist-info/top_level.txt
odoo_addon_stock_picking_group_by_max_weight-16.0.1.1.1.dist-info/RECORD
